nb_risk/__init__.py
nb_risk/admin.py
nb_risk/choices.py
nb_risk/columns.py
nb_risk/custom_views.py
nb_risk/cve.py
nb_risk/filtersets.py
nb_risk/forms.py
nb_risk/middleware.py
nb_risk/models.py
nb_risk/navigation.py
nb_risk/signals.py
nb_risk/tables.py
nb_risk/template_content.py
nb_risk/urls.py
nb_risk/version.py
nb_risk/views.py
nb_risk/api/__init__.py
nb_risk/api/serializers.py
nb_risk/api/urls.py
nb_risk/api/views.py
nb_risk/migrations/0001_initial.py
nb_risk/migrations/0002_vulnerability_cvssaccesscomplexity_and_more.py
nb_risk/migrations/0003_control.py
nb_risk/migrations/0004_alter_vulnerability_options.py
nb_risk/migrations/0005_alter_vulnerability_cvssbasescore.py
nb_risk/migrations/0006_vulnerability_unique_vuln_name.py
nb_risk/migrations/0007_remove_vulnerability_unique_vuln_name_and_more.py
nb_risk/migrations/__init__.py
nb_risk/templates/nb_risk/control.html
nb_risk/templates/nb_risk/control_assets.html
nb_risk/templates/nb_risk/control_risks.html
nb_risk/templates/nb_risk/generic_vulnerability_assignment_edit.html
nb_risk/templates/nb_risk/generic_vulnerability_list.html
nb_risk/templates/nb_risk/risk.html
nb_risk/templates/nb_risk/threatevent.html
nb_risk/templates/nb_risk/threatevent_vulnerabilities.html
nb_risk/templates/nb_risk/threatsource.html
nb_risk/templates/nb_risk/vulnerability.html
nb_risk/templates/nb_risk/vulnerability_affected_assets.html
nb_risk/templates/nb_risk/vulnerability_assignment_button.html
nb_risk/templates/nb_risk/vulnerability_list.html
nb_risk/templates/nb_risk/vulnerability_search.html
nb_risk/tests/__init__.py
nb_risk/tests/custom.py
nb_risk/tests/control/__init__.py
nb_risk/tests/threatsource/__init__.py
nb_risk/tests/threatsource/test_api.py
nb_risk/tests/threatsource/test_filters.py
nb_risk/tests/threatsource/test_views.py
nb_risk/tests/vulnerability/__init__.py
nb_risk/tests/vulnerability/test_filters.py
nb_risk/tests/vulnerability/test_views.py
nb_risk/tests/vulnerabilityassignment/__init__.py
NbRisk-41.0.2.dist-info/LICENSE
NbRisk-41.0.2.dist-info/METADATA
NbRisk-41.0.2.dist-info/WHEEL
NbRisk-41.0.2.dist-info/top_level.txt
NbRisk-41.0.2.dist-info/RECORD
