Metadata-Version: 2.1
Name: NbRisk
Version: 41.0.2
Summary: NIST 800-30 Risk Management for Netbox
Home-page: https://github.com/renatoalmeidaoliveira/nbrisk
Author: Renato Almdida Oliveira
Author-email: renato.almeida.oliveira@gmail.com
Classifier: Development Status :: 2 - Pre-Alpha
Classifier: Framework :: Django
Classifier: Programming Language :: Python :: 3
License-File: LICENSE
